{
  "question": "What are the hiring trends in the technology sector across different companies?",
  "subtasks": "[\n    {\n        \"step\": 1,\n        \"task\": \"Identify all companies operating in the technology sector and gather their details.\",\n        \"table\": [\"CompanyInfo\"]\n    },\n    {\n        \"step\": 2,\n        \"task\": \"Collect hiring data for the identified technology companies, including job roles, responsibilities, and requirements.\",\n        \"table\": [\"CompanyHiringDetail\"]\n    },\n    {\n        \"step\": 3,\n        \"task\": \"Analyze the hiring data to identify trends, such as most common job roles, skills in demand, and geographical distribution of job postings.\",\n        \"table\": [\"CompanyHiringDetail\"]\n    },\n    {\n        \"step\": 4,\n        \"task\": \"Cross-reference the hiring data with the company profiles to provide insights on company sizes, budgets, and revenue to explain certain hiring trends.\",\n        \"table\": [\"CompanyInfo\", \"CompanyHiringDetail\"]\n    },\n    {\n        \"step\": 5,\n        \"task\": \"Compile a report summarizing the hiring trends in the technology sector and insights derived from the analysis.\",\n        \"table\": []\n    }\n]"
}