{
  "question": "What are the current hiring trends in the technology sector across different companies?",
  "subtasks": "[{\"step\":1,\"task\":\"Identify technological domains with active job listings from the CompanyHiringDetail table.\",\"table\":[\"CompanyHiringDetail\"]},{\"step\":2,\"task\":\"Gather data on companies actively hiring in identified domains from CompanyInfo and CompanyHiringDetail tables.\",\"table\":[\"CompanyInfo\",\"CompanyHiringDetail\"]},{\"step\":3,\"task\":\"Analyze the geographic distribution of hiring trends by correlating city data in the CompanyDataCenter and CompanyHiringDetail tables.\",\"table\":[\"CompanyDataCenter\",\"CompanyHiringDetail\"]},{\"step\":4,\"task\":\"Aggregate hiring data to identify trends in job designations and required skills by analyzing CompanyHiringDetail table insights.\",\"table\":[\"CompanyHiringDetail\"]},{\"step\":5,\"task\":\"Summarize technology sector hiring trends based on analysis and prepare insights for reporting.\",\"table\":[\"CompanyHiringDetail\"]}]}"
}