{
  "question": "What are the social media engagement trends of companies in the technology industry?",
  "subtasks": "[{\"step\":1,\"task\":\"Query the CompanyInfo table to identify all companies in the technology industry.\",\"table\":[\"CompanyInfo\"]},{\"step\":2,\"task\":\"Aggregate social media engagement metrics from SocialMediaInfo for the identified companies to analyze trends.\",\"table\":[\"SocialMediaInfo\"]},{\"step\":3,\"task\":\"Extract and analyze detailed engagement data from each social media platform (Facebook, Instagram, Twitter, and YouTube) for the technology companies.\",\"table\":[\"CompanyFacebookDetail\",\"CompanyInstagramDetail\",\"CompanyTwitterDetail\",\"CompanyYoutubeDetail\"]},{\"step\":4,\"task\":\"Compile the findings into a report summarizing the trends in social media engagement across the technology companies.\",\"table\":[\"CompanyInfo\",\"SocialMediaInfo\",\"CompanyFacebookDetail\",\"CompanyInstagramDetail\",\"CompanyTwitterDetail\",\"CompanyYoutubeDetail\"]}]}"
}