{
  "question": "How do augmented and virtual reality deployments reinforce media enterprises' content engagement goals?",
  "subtasks": [
    {
      "step": 1,
      "task": "Identify media enterprises mentioned in leadership excerpts related to AR/VR deployments.",
      "table": [
        "PersonaMisc"
      ]
    },
    {
      "step": 2,
      "task": "Extract content engagement goals from social media posts.",
      "table": [
        "PersonaTwitterTweets"
      ]
    },
    {
      "step": 3,
      "task": "Analyze the relationship between AR/VR deployments and content engagement goals.",
      "table": [
        "PersonaMisc"
      ]
    }
  ]
}