{
  "question": "Which high-growth companies have redirected focus towards enhanced mobility technology solutions?",
  "subtasks": [
    {
      "step": 1,
      "task": "Identify high-growth companies from the available data.",
      "table": [
        "PersonaTitle"
      ]
    },
    {
      "step": 2,
      "task": "Filter the identified companies for those focusing on mobility technology solutions.",
      "table": [
        "PersonaTitle"
      ]
    },
    {
      "step": 3,
      "task": "Extract relevant details about the focus on mobility technology solutions.",
      "table": [
        "PersonaTitle"
      ]
    }
  ]
}