{
  "question": "How are companies aligning their IT strategies with newly hired senior executives\u2019 expertise?",
  "subtasks": [
    {
      "step": 1,
      "task": "Identify newly hired senior executives and their expertise.",
      "table": [
        "CompanyTwitterDetail"
      ]
    },
    {
      "step": 2,
      "task": "Find companies aligning their IT strategies with this expertise.",
      "table": [
        "CompanyTwitterDetail"
      ]
    },
    {
      "step": 3,
      "task": "Describe the alignment between IT strategies and executives\u2019 expertise.",
      "table": [
        "CompanyTwitterDetail"
      ]
    }
  ]
}