{
  "question": "Which companies are prioritizing artificial intelligence and have concurrently seen increased interest in leadership changes?",
  "subtasks": [
    {
      "step": 1,
      "task": "Identify companies prioritizing artificial intelligence from industry trends.",
      "table": [
        "IndustryBusinessTrend"
      ]
    },
    {
      "step": 2,
      "task": "Find companies with increased interest in leadership changes from social media posts.",
      "table": [
        "SocialMediaInfo"
      ]
    },
    {
      "step": 3,
      "task": "Combine results to find companies that meet both criteria.",
      "table": []
    }
  ]
}