{
  "question": "Among the companies that have increased IT spending, which ones are investing in AI technologies?",
  "subtasks": [
    {
      "step": 1,
      "task": "Identify companies that have increased IT spending.",
      "table": [
        "PersonaLinkedinActivity"
      ]
    },
    {
      "step": 2,
      "task": "Filter companies investing in AI technologies.",
      "table": [
        "PersonaLinkedinActivity"
      ]
    },
    {
      "step": 3,
      "task": "List companies that are both increasing IT spending and investing in AI.",
      "table": []
    }
  ]
}