{
  "question": "What new products are being developed by companies with a recent spike in Facebook interactions?",
  "subtasks": [
    {
      "step": 1,
      "task": "Identify companies with a recent spike in Facebook interactions.",
      "table": [
        "PersonaLinkedInProfile"
      ]
    },
    {
      "step": 2,
      "task": "Extract information on new products being developed by these companies.",
      "table": [
        "CompanyVendorTechDetail"
      ]
    },
    {
      "step": 3,
      "task": "List new products from companies with increased Facebook interactions.",
      "table": [
        "CompanyVendorTechDetail"
      ]
    }
  ]
}