{
  "question": "What companies hired additional cloud computing experts and have been mentioned in industry business trend discussions?",
  "subtasks": [
    {
      "step": 1,
      "task": "Identify companies that hired additional cloud computing experts.",
      "table": [
        "PersonaLinkedInProfile"
      ]
    },
    {
      "step": 2,
      "task": "Find companies mentioned in industry business trend discussions.",
      "table": [
        "CompanyLeadershipExcerpt"
      ]
    },
    {
      "step": 3,
      "task": "Combine results to find companies meeting both criteria.",
      "table": []
    }
  ]
}