{
  "question": "What major cryptocurrency investments were made by companies recently gaining publicity on LinkedIn?",
  "subtasks": [
    {
      "step": 1,
      "task": "Identify companies gaining publicity on LinkedIn from PersonaLinkedInProfile.",
      "table": [
        "PersonaLinkedInProfile"
      ]
    },
    {
      "step": 2,
      "task": "Extract major cryptocurrency investments made by these companies.",
      "table": [
        "PersonaLinkedInProfile"
      ]
    },
    {
      "step": 3,
      "task": "Correlate the investments with the companies gaining publicity.",
      "table": [
        "PersonaLinkedInProfile"
      ]
    }
  ]
}