{
  "question": "What are the social media engagement trends of technology companies in the healthcare industry?",
  "subtasks": ":[{\"step\":1,\"task\":\"Identify all technology companies that fall under the healthcare industry category.\",\"table\":[\"CompanyInfo\"]},{\"step\":2,\"task\":\"Collect social media engagement metrics (likes, comments, engagement rates) from relevant social media tables for the identified healthcare companies.\",\"table\":[\"CompanyFacebookDetail\",\"CompanyInstagramDetail\",\"CompanyTwitterDetail\",\"CompanyYoutubeDetail\"]},{\"step\":3,\"task\":\"Analyze the engagement trends over a specified time period to assess growth or decline in interactions for each platform.\",\"table\":[\"CompanyFacebookDetail\",\"CompanyInstagramDetail\",\"CompanyTwitterDetail\",\"CompanyYoutubeDetail\"]},{\"step\":4,\"task\":\"Generate a report detailing the engagement metrics, trends, and insights for the healthcare technology companies.\",\"table\":[\"CompanyInfo\",\"CompanyFacebookDetail\",\"CompanyInstagramDetail\",\"CompanyTwitterDetail\",\"CompanyYoutubeDetail\"]}]}"
}