{
  "question": "Analyze the technology adoption trends of companies in the healthcare industry.",
  "subtasks": [
    {
      "step": 1,
      "task": "Identify all companies operating in the healthcare industry from the CompanyInfo table.",
      "table": [
        "CompanyInfo"
      ]
    },
    {
      "step": 2,
      "task": "Gather technology stack details for the identified companies from the CompanyTechStack table.",
      "table": [
        "CompanyTechStack"
      ]
    },
    {
      "step": 3,
      "task": "Analyze the IT focus areas for each identified healthcare company using the CompanyFocusAreaDetail table.",
      "table": [
        "CompanyFocusAreaDetail"
      ]
    },
    {
      "step": 4,
      "task": "Review relevant vendor product details and services used by these companies from the CompanyVendorProductDetail and CompanyVendorTechDetail tables.",
      "table": [
        "CompanyVendorProductDetail",
        "CompanyVendorTechDetail"
      ]
    },
    {
      "step": 5,
      "task": "Compile the findings to summarize the overall technology adoption trends specifically for the healthcare industry.",
      "table": [
        "CompanyInfo",
        "CompanyTechStack",
        "CompanyFocusAreaDetail",
        "CompanyVendorProductDetail",
        "CompanyVendorTechDetail"
      ]
    }
  ]
}