{
  "question": "How do changes in vendor technology options affect company pursuits within big data and analytics?",
  "subtasks": [
    {
      "step": 1,
      "task": "Identify changes in vendor technology options.",
      "table": [
        "CompanyManagementDetail"
      ]
    },
    {
      "step": 2,
      "task": "Determine company pursuits related to big data and analytics.",
      "table": [
        "CompanyManagementDetail"
      ]
    },
    {
      "step": 3,
      "task": "Analyze the impact of vendor technology changes on these pursuits.",
      "table": [
        "CompanyManagementDetail"
      ]
    }
  ]
}