{
  "question": "Which companies currently seeking blockchain vendors are also noted for extensive IT hiring strategies?",
  "subtasks": [
    {
      "step": 1,
      "task": "Identify companies seeking blockchain vendors.",
      "table": [
        "CompanyInfo"
      ]
    },
    {
      "step": 2,
      "task": "Extract IT hiring strategies for these companies.",
      "table": [
        "CompanyManagementDetail"
      ]
    },
    {
      "step": 3,
      "task": "Match companies with both blockchain vendor needs and extensive IT hiring strategies.",
      "table": [
        "IndustryBusinessTrend"
      ]
    }
  ]
}