{
  "question": "Who among personas identified as technologists have highlighted AI advancements in their Instagram posts?",
  "subtasks": [
    {
      "step": 1,
      "task": "Identify personas categorized as technologists.",
      "table": [
        "CompanyManagementDetail"
      ]
    },
    {
      "step": 2,
      "task": "Extract Instagram posts related to AI advancements.",
      "table": [
        "IndustryBusinessTrend"
      ]
    },
    {
      "step": 3,
      "task": "Match technologist personas with their Instagram posts on AI advancements.",
      "table": [
        "CompanyManagementDetail",
        "IndustryBusinessTrend"
      ]
    }
  ]
}