{
  "question": "Which industries are seeing a new wave of data-focused strategies based on promotions revealed in management details?",
  "subtasks": [
    {
      "step": 1,
      "task": "Identify promotions related to data-focused strategies in management details.",
      "table": [
        "CompanyManagementDetail"
      ]
    },
    {
      "step": 2,
      "task": "Extract industries associated with these promotions.",
      "table": [
        "CompanyInfo"
      ]
    },
    {
      "step": 3,
      "task": "Determine which industries are experiencing a new wave of data-focused strategies.",
      "table": [
        "CompanyManagementDetail",
        "CompanyInfo"
      ]
    }
  ]
}