{
  "question": "Which personas have been quoted in LinkedIn news articles for innovations in neural networks and are linked to companies expanding AI research labs?",
  "subtasks": [
    {
      "step": 1,
      "task": "Identify personas quoted in LinkedIn news articles for neural network innovations.",
      "table": [
        "PersonaYoutubeProfile"
      ]
    },
    {
      "step": 2,
      "task": "Identify companies expanding AI research labs.",
      "table": [
        "CompanyDataCenter"
      ]
    },
    {
      "step": 3,
      "task": "Link personas to companies expanding AI research labs.",
      "table": []
    }
  ]
}