{
  "question": "What distinctive competencies do leaders project within the cloud-native transition landscape?",
  "subtasks": [
    {
      "step": 1,
      "task": "Identify leaders involved in cloud-native transitions.",
      "table": [
        "SectionInfo"
      ]
    },
    {
      "step": 2,
      "task": "Extract competencies mentioned in leadership excerpts.",
      "table": [
        "PersonaMisc"
      ]
    },
    {
      "step": 3,
      "task": "Determine distinctive competencies projected by these leaders.",
      "table": [
        "SectionInfo",
        "PersonaMisc"
      ]
    }
  ]
}