{
  "question": "What companies announcing expansions in their data centers simultaneously promote their focus on AI in social media?",
  "subtasks": [
    {
      "step": 1,
      "task": "Identify companies announcing expansions in their data centers from the IndustryBusinessTrend table.",
      "table": [
        "IndustryBusinessTrend"
      ]
    },
    {
      "step": 2,
      "task": "Extract social media content promoting AI focus from the PersonaYoutubeProfile table.",
      "table": [
        "PersonaYoutubeProfile"
      ]
    },
    {
      "step": 3,
      "task": "Determine which companies both announce data center expansions and promote AI on social media.",
      "table": [
        "IndustryBusinessTrend",
        "PersonaYoutubeProfile"
      ]
    }
  ]
}