{
  "question": "Which tech firms are leveraging Twitter for customer engagement after adopting new technologies?",
  "subtasks": [
    {
      "step": 1,
      "task": "Identify tech firms adopting new technologies.",
      "table": [
        "CompanyFocusAreaDetail"
      ]
    },
    {
      "step": 2,
      "task": "Find firms leveraging Twitter for customer engagement.",
      "table": [
        "PersonaInstagramProfile"
      ]
    },
    {
      "step": 3,
      "task": "List tech firms using Twitter for engagement post-technology adoption.",
      "table": []
    }
  ]
}