{
  "question": "What is the current social media engagement trend across different companies in the technology industry?",
  "subtasks": [
    {
      "step": 1,
      "task": "Gather engagement metrics from Facebook, Twitter, Instagram, and YouTube for companies in the technology industry.",
      "table": [
        "CompanyFacebookDetail",
        "CompanyTwitterDetail",
        "CompanyInstagramDetail",
        "CompanyYoutubeDetail"
      ]
    },
    {
      "step": 2,
      "task": "Filter companies in the technology industry from the CompanyInfo table.",
      "table": [
        "CompanyInfo"
      ]
    },
    {
      "step": 3,
      "task": "Combine the engagement data with the corresponding companies' IDs to analyze the overall trend of social media engagement for technology companies.",
      "table": [
        "CompanyFacebookDetail",
        "CompanyTwitterDetail",
        "CompanyInstagramDetail",
        "CompanyYoutubeDetail",
        "CompanyInfo"
      ]
    },
    {
      "step": 4,
      "task": "Identify major social media platforms used by technology companies based on the available engagement data.",
      "table": [
        "SocialMediaInfo"
      ]
    }
  ]
}