{
  "question": "How do Instagram engagement increases shape leadership viewpoints across electronics firms?",
  "subtasks": [
    {
      "step": 1,
      "task": "Identify Instagram engagement metrics related to electronics firms.",
      "table": [
        "PersonaMisc"
      ]
    },
    {
      "step": 2,
      "task": "Extract leadership viewpoints from these firms.",
      "table": [
        "PersonaTitle"
      ]
    },
    {
      "step": 3,
      "task": "Analyze how increased engagement shapes these leadership viewpoints.",
      "table": [
        "PersonaMisc"
      ]
    }
  ]
}