{
  "question": "Which companies have tech stacks focused on hybrid cloud models, and how does this reflect in their business trends?",
  "subtasks": [
    {
      "step": 1,
      "task": "Identify companies with tech stacks focused on hybrid cloud models.",
      "table": [
        "CompanyInfo"
      ]
    },
    {
      "step": 2,
      "task": "Extract business trends for these companies.",
      "table": [
        "SectionTitle"
      ]
    },
    {
      "step": 3,
      "task": "Analyze how the focus on hybrid cloud models reflects in their business trends.",
      "table": [
        "PersonaMisc"
      ]
    }
  ]
}