{
  "question": "Which data scientists are actively contributing to discussions on cloud computing in their LinkedIn posts?",
  "subtasks": [
    {
      "step": 1,
      "task": "Identify data scientists from the PersonaYoutubeProfile table.",
      "table": [
        "PersonaYoutubeProfile"
      ]
    },
    {
      "step": 2,
      "task": "Filter LinkedIn posts related to cloud computing.",
      "table": [
        "PersonaYoutubeProfile"
      ]
    },
    {
      "step": 3,
      "task": "Combine the results to find data scientists contributing to cloud computing discussions.",
      "table": [
        "PersonaYoutubeProfile"
      ]
    }
  ]
}