{
  "question": "Which companies have strategically increased their YouTube content on AI ethics and have influential thought leaders?",
  "subtasks": [
    {
      "step": 1,
      "task": "Identify companies that have increased YouTube content on AI ethics from the PersonaYoutubeProfile table.",
      "table": [
        "PersonaYoutubeProfile"
      ]
    },
    {
      "step": 2,
      "task": "Identify influential thought leaders associated with these companies.",
      "table": [
        "PersonaYoutubeProfile"
      ]
    },
    {
      "step": 3,
      "task": "Correlate the increase in YouTube content with the presence of thought leaders.",
      "table": [
        "PersonaYoutubeProfile"
      ]
    }
  ]
}