{
  "question": "Which sectors prioritize augmented intelligence alongside expanding their social reach on Twitter?",
  "subtasks": [
    {
      "step": 1,
      "task": "Identify sectors prioritizing augmented intelligence.",
      "table": [
        "CompanyFocusAreaDetail"
      ]
    },
    {
      "step": 2,
      "task": "Determine sectors expanding their social reach on Twitter.",
      "table": [
        "PersonaMisc"
      ]
    },
    {
      "step": 3,
      "task": "List sectors that prioritize both augmented intelligence and social reach expansion.",
      "table": []
    }
  ]
}