{
  "question": "Analyze the social media engagement trends of companies within the tech industry over the last year.",
  "subtasks": [
    {
      "step": 1,
      "task": "Identify companies within the technology industry from the CompanyInfo table.",
      "table": [
        "CompanyInfo"
      ]
    },
    {
      "step": 2,
      "task": "Retrieve social media engagement metrics from the SocialMediaInfo table for identified tech companies.",
      "table": [
        "SocialMediaInfo"
      ]
    },
    {
      "step": 3,
      "task": "Aggregate engagement data from various social media platforms to analyze overall trends for the past year.",
      "table": [
        "CompanyFacebookDetail",
        "CompanyTwitterDetail",
        "CompanyInstagramDetail",
        "CompanyYoutubeDetail"
      ]
    },
    {
      "step": 4,
      "task": "Compare the engagement trends with IT budget and revenue data from CompanyInfo to determine correlation.",
      "table": [
        "CompanyInfo"
      ]
    },
    {
      "step": 5,
      "task": "Compile a report summarizing findings and insights from the analysis of social media engagement and IT budgets.",
      "table": [
        "CompanyInfo",
        "SectionData"
      ]
    }
  ]
}