{
  "question": "What are the technology adoption trends across different industries and how do they relate to company strategies?",
  "subtasks": "[{\"step\": 1, \"task\": \"Identify the industries of interest that are showing technology adoption trends.\", \"table\": [\"IndustryITTrend\"]}, {\"step\": 2, \"task\": \"Gather data on specific technology focuses adopted by companies within these industries.\", \"table\": [\"CompanyFocusAreaDetail\"]}, {\"step\": 3, \"task\": \"Analyze the financial metrics of companies adopting these technologies to assess their business strategy outcomes.\", \"table\": [\"CompanyInfo\"]}, {\"step\": 4, \"task\": \"Compile social media engagement metrics to see if there's a correlation between tech adoption and public perception.\", \"table\": [\"SocialMediaInfo\"]}, {\"step\": 5, \"task\": \"Review vendor partnerships and the technologies provided to understand industry reliance on third-party solutions.\", \"table\": [\"CompanyITPartnerDetail\"]}]"
}