{
  "question": "What are the most common data visualization tools mentioned by companies with a significant online following?",
  "subtasks": [
    {
      "step": 1,
      "task": "Identify companies with high online engagement.",
      "table": ["CompanyTwitterDetail"]
    },
    {
      "step": 2,
      "task": "Extract data visualization tools used by those companies.",
      "table": ["CompanyTechStack"]
    },
    {
      "step": 3,
      "task": "Rank the most commonly used visualization tools.",
      "table": []
    }
  ]
}
