{
  "question": "Which companies have increased their investment in data analytics technologies within the last year?",
  "subtasks": [
    {
      "step": 1,
      "task": "Identify companies that have made recent investments in data analytics technologies. [CompanyTechStack]",
      "table": [
        "CompanyTechStack"
      ]
    },
    {
      "step": 2,
      "task": "Filter the investments to those made within the last year. [CompanyTechStack]",
      "table": [
        "CompanyTechStack"
      ]
    },
    {
      "step": 3,
      "task": "Cross-reference with any relevant deal information to confirm increased investment. [CompanyDealMaster]",
      "table": [
        "CompanyDealMaster"
      ]
    }
  ]
}